flask_adminlte3/__init__.py
flask_adminlte3/static/css/adminlte.css
flask_adminlte3/static/css/adminlte.css.map
flask_adminlte3/static/css/adminlte.min.css
flask_adminlte3/static/css/adminlte.min.css.map
flask_adminlte3/static/css/alt/adminlte.components.css
flask_adminlte3/static/css/alt/adminlte.components.css.map
flask_adminlte3/static/css/alt/adminlte.components.min.css
flask_adminlte3/static/css/alt/adminlte.components.min.css.map
flask_adminlte3/static/css/alt/adminlte.core.css
flask_adminlte3/static/css/alt/adminlte.core.css.map
flask_adminlte3/static/css/alt/adminlte.core.min.css
flask_adminlte3/static/css/alt/adminlte.core.min.css.map
flask_adminlte3/static/css/alt/adminlte.extra-components.css
flask_adminlte3/static/css/alt/adminlte.extra-components.css.map
flask_adminlte3/static/css/alt/adminlte.extra-components.min.css
flask_adminlte3/static/css/alt/adminlte.extra-components.min.css.map
flask_adminlte3/static/css/alt/adminlte.pages.css
flask_adminlte3/static/css/alt/adminlte.pages.css.map
flask_adminlte3/static/css/alt/adminlte.pages.min.css
flask_adminlte3/static/css/alt/adminlte.pages.min.css.map
flask_adminlte3/static/css/alt/adminlte.plugins.css
flask_adminlte3/static/css/alt/adminlte.plugins.css.map
flask_adminlte3/static/css/alt/adminlte.plugins.min.css
flask_adminlte3/static/css/alt/adminlte.plugins.min.css.map
flask_adminlte3/static/img/AdminLTELogo.png
flask_adminlte3/static/img/avatar.png
flask_adminlte3/static/js/adminlte.js
flask_adminlte3/static/js/adminlte.js.map
flask_adminlte3/static/js/adminlte.min.js
flask_adminlte3/static/js/adminlte.min.js.map
flask_adminlte3/static/plugins/bootstrap/js/bootstrap.bundle.js
flask_adminlte3/static/plugins/bootstrap/js/bootstrap.bundle.js.map
flask_adminlte3/static/plugins/bootstrap/js/bootstrap.bundle.min.js
flask_adminlte3/static/plugins/bootstrap/js/bootstrap.bundle.min.js.map
flask_adminlte3/static/plugins/bootstrap/js/bootstrap.js
flask_adminlte3/static/plugins/bootstrap/js/bootstrap.js.map
Flask_AdminLTE3-1.0.4.dist-info/LICENSE
Flask_AdminLTE3-1.0.4.dist-info/METADATA
Flask_AdminLTE3-1.0.4.dist-info/WHEEL
Flask_AdminLTE3-1.0.4.dist-info/top_level.txt
Flask_AdminLTE3-1.0.4.dist-info/RECORD
