Metadata-Version: 2.1
Name: Flask-AdminLTE3
Version: 1.0.4
Summary: AdminLTE3 Theme for Flask-Admin.
Home-page: https://github.com/shijl0925/Flask-AdminLTE3
Author: Jialiang Shi
Author-email: kevin09254930sjl@gmail.com
License: MIT
Platform: any
Classifier: Environment :: Web Environment
Classifier: Intended Audience :: Developers
Classifier: License :: OSI Approved :: BSD License
Classifier: Operating System :: OS Independent
Classifier: Programming Language :: Python :: 3
Classifier: Topic :: Software Development :: Libraries :: Python Modules
Requires-Dist: flask-admin (>=1.5.7)
Requires-Dist: Flask (>=0.8)
